ShiyanlouScalaJiaochengHeji20160904/README.md
ShiyanlouScalaJiaochengHeji20160904/__init__.py
ShiyanlouScalaJiaochengHeji20160904/__main__.py
ShiyanlouScalaJiaochengHeji20160904/file.epub
ShiyanlouScalaJiaochengHeji20160904/index.html
ShiyanlouScalaJiaochengHeji20160904/css/__init__.py
ShiyanlouScalaJiaochengHeji20160904/css/annotations.css
ShiyanlouScalaJiaochengHeji20160904/css/main.css
ShiyanlouScalaJiaochengHeji20160904/css/normalize.css
ShiyanlouScalaJiaochengHeji20160904/css/popup.css
ShiyanlouScalaJiaochengHeji20160904/font/__init__.py
ShiyanlouScalaJiaochengHeji20160904/font/fontello.eot
ShiyanlouScalaJiaochengHeji20160904/font/fontello.svg
ShiyanlouScalaJiaochengHeji20160904/font/fontello.ttf
ShiyanlouScalaJiaochengHeji20160904/font/fontello.woff
ShiyanlouScalaJiaochengHeji20160904/img/__init__.py
ShiyanlouScalaJiaochengHeji20160904/img/annotator-glyph-sprite.png
ShiyanlouScalaJiaochengHeji20160904/img/annotator-icon-sprite.png
ShiyanlouScalaJiaochengHeji20160904/img/apple-touch-icon.png
ShiyanlouScalaJiaochengHeji20160904/img/cancelfullscreen.png
ShiyanlouScalaJiaochengHeji20160904/img/close.png
ShiyanlouScalaJiaochengHeji20160904/img/fullscreen.png
ShiyanlouScalaJiaochengHeji20160904/img/loader.gif
ShiyanlouScalaJiaochengHeji20160904/img/menu-icon.png
ShiyanlouScalaJiaochengHeji20160904/img/save.png
ShiyanlouScalaJiaochengHeji20160904/img/saved.png
ShiyanlouScalaJiaochengHeji20160904/img/settings-s.png
ShiyanlouScalaJiaochengHeji20160904/img/settings.png
ShiyanlouScalaJiaochengHeji20160904/img/star.png
ShiyanlouScalaJiaochengHeji20160904/js/__init__.py
ShiyanlouScalaJiaochengHeji20160904/js/epub.js
ShiyanlouScalaJiaochengHeji20160904/js/epub.min.js
ShiyanlouScalaJiaochengHeji20160904/js/epub.min.map
ShiyanlouScalaJiaochengHeji20160904/js/hooks.min.js
ShiyanlouScalaJiaochengHeji20160904/js/hooks.min.map
ShiyanlouScalaJiaochengHeji20160904/js/reader.js
ShiyanlouScalaJiaochengHeji20160904/js/reader.js.map
ShiyanlouScalaJiaochengHeji20160904/js/reader.min.js
shiyanlou_scala_jiaocheng_heji_20160904-2024.3.2.0.dist-info/METADATA
shiyanlou_scala_jiaocheng_heji_20160904-2024.3.2.0.dist-info/WHEEL
shiyanlou_scala_jiaocheng_heji_20160904-2024.3.2.0.dist-info/entry_points.txt
shiyanlou_scala_jiaocheng_heji_20160904-2024.3.2.0.dist-info/top_level.txt
shiyanlou_scala_jiaocheng_heji_20160904-2024.3.2.0.dist-info/RECORD
